py_tools_wd/__init__.py
py_tools_wd/ai/__init__.py
py_tools_wd/ai/face_clip.py
py_tools_wd/ai/face_pyr.py
py_tools_wd/base/__init__.py
py_tools_wd/base/download.py
py_tools_wd/base/file_combo.py
py_tools_wd/base/log_config.py
py_tools_wd/base/log_setting.py
py_tools_wd/base/time_util.py
py_tools_wd/base/timeit.py
py_tools_wd/base/tpm.py
py_tools_wd/image/AlibabaPuHuiTi-3-65-Medium.ttf
py_tools_wd/image/__init__.py
py_tools_wd/image/coord.py
py_tools_wd/image/cv_draw.py
py_tools_wd/image/image_converter.py
py_tools_wd/image/image_draw.py
py_tools_wd/mq/__init__.py
py_tools_wd/mq/channel.py
py_tools_wd/mq/kafka.py
py_tools_wd/mq/rabbitmq.py
py_tools_wd/video/__init__.py
py_tools_wd/video/cv_tools.py
py_tools_wd/video/grab_frame.py
py_tools_wd/video/random_frame.py
py_tools_wd-0.2.5.dist-info/METADATA
py_tools_wd-0.2.5.dist-info/WHEEL
py_tools_wd-0.2.5.dist-info/top_level.txt
py_tools_wd-0.2.5.dist-info/RECORD
