Metadata-Version: 2.4
Name: py_tools_wd
Version: 0.2.5
Summary: wdx tools
Author-email: wangdongxu <wangdongxudyx@163.com>
License: Apache-2.0
Classifier: Programming Language :: Python :: 3
Classifier: License :: OSI Approved :: Apache Software License
Classifier: Operating System :: OS Independent
Requires-Python: >=3.9
